[
  {
    "resource": "schoolYearTypes",
    "path": "/ed-fi/schoolYearTypes",
    "onlyInSwagger": [
      {
        "name": "schoolYear",
        "description": "Key for School Year",
        "schema": {
          "type": "integer",
          "format": "int32"
        },
        "isRef": false
      },
      {
        "name": "currentSchoolYear",
        "description": "The code for the current school year.",
        "schema": {
          "type": "boolean"
        },
        "isRef": false
      },
      {
        "name": "schoolYearDescription",
        "description": "The description for the SchoolYear type.",
        "schema": {
          "maxLength": 50,
          "type": "string"
        },
        "isRef": false
      }
    ],
    "onlyInDs52": [],
    "parameterDifferences": [],
    "queryFieldsOnlyInSwagger": [
      "id"
    ],
    "queryFieldsOnlyInDs52": []
  }
]